redis_data_structures/__init__.py
redis_data_structures/base.py
redis_data_structures/bloom_filter.py
redis_data_structures/config.py
redis_data_structures/connection.py
redis_data_structures/deque.py
redis_data_structures/dict.py
redis_data_structures/exceptions.py
redis_data_structures/graph.py
redis_data_structures/hash_map.py
redis_data_structures/health.py
redis_data_structures/logging.py
redis_data_structures/lru_cache.py
redis_data_structures/priority_queue.py
redis_data_structures/py.typed
redis_data_structures/queue.py
redis_data_structures/ring_buffer.py
redis_data_structures/serializer.py
redis_data_structures/set.py
redis_data_structures/stack.py
redis_data_structures/trie.py
redis_data_structures-0.1.28.dist-info/METADATA
redis_data_structures-0.1.28.dist-info/WHEEL
redis_data_structures-0.1.28.dist-info/licenses/LICENSE
redis_data_structures-0.1.28.dist-info/RECORD
