Metadata-Version: 2.4
Name: redis-data-structures
Version: 0.1.28
Summary: Redis-backed data structures for building scalable and resilient applications
Project-URL: Homepage, https://github.com/vndee/redis-data-structures
Project-URL: Repository, https://github.com/vndee/redis-data-structures
Project-URL: Documentation, https://github.com/vndee/redis-data-structures#readme
Author-email: "Duy V. Huynh" <vndee.huynh@gmail.com>
License: MIT License
License-File: LICENSE
Keywords: bloom-filter,data-structures,deque,graph,hash-map,lru-cache,priority-queue,queue,redis,ring-buffer,set,stack
Classifier: Development Status :: 4 - Beta
Classifier: Intended Audience :: Developers
Classifier: License :: OSI Approved :: MIT License
Classifier: Programming Language :: Python :: 3.8
Classifier: Programming Language :: Python :: 3.9
Classifier: Programming Language :: Python :: 3.10
Classifier: Programming Language :: Python :: 3.11
Classifier: Topic :: Database
Classifier: Topic :: Software Development :: Libraries :: Python Modules
Requires-Python: >=3.8
Requires-Dist: backoff>=2.2.1
Requires-Dist: pyyaml>=6.0.1
Requires-Dist: redis>=4.5.0
Provides-Extra: orjson
Requires-Dist: orjson>=3.9.10; extra == 'orjson'
Provides-Extra: pydantic
Requires-Dist: pydantic>=2.5.3; extra == 'pydantic'
